projen_jsii/__init__.py
projen_jsii/py.typed
projen_jsii/_jsii/__init__.py
projen_jsii/_jsii/projen-jsii@0.0.6.jsii.tgz
projen_jsii-0.0.6.dist-info/LICENSE
projen_jsii-0.0.6.dist-info/METADATA
projen_jsii-0.0.6.dist-info/WHEEL
projen_jsii-0.0.6.dist-info/top_level.txt
projen_jsii-0.0.6.dist-info/RECORD
