Metadata-Version: 2.1
Name: projen-jsii
Version: 0.0.6
Summary: projen-jsii
Home-page: https://github.com/daveshepherd/projen-jsii.git
Author: Dave Shepherd<dave.shepherd@endor.me.uk>
License: Apache-2.0
Project-URL: Source, https://github.com/daveshepherd/projen-jsii.git
Classifier: Intended Audience :: Developers
Classifier: Operating System :: OS Independent
Classifier: Programming Language :: JavaScript
Classifier: Programming Language :: Python :: 3 :: Only
Classifier: Programming Language :: Python :: 3.8
Classifier: Programming Language :: Python :: 3.9
Classifier: Programming Language :: Python :: 3.10
Classifier: Programming Language :: Python :: 3.11
Classifier: Typing :: Typed
Classifier: Development Status :: 5 - Production/Stable
Classifier: License :: OSI Approved
Requires-Python: ~=3.8
License-File: LICENSE
Requires-Dist: constructs ==10.3.0
Requires-Dist: jsii <2.0.0,>=1.101.0
Requires-Dist: projen ==0.82.8
Requires-Dist: publication >=0.0.3
Requires-Dist: typeguard ~=2.13.3
